testupload/main.py
testupload123-0.1.1.dist-info/WHEEL
testupload123-0.1.1.dist-info/METADATA
testupload123-0.1.1.dist-info/RECORD
