Metadata-Version: 2.1
Name: testupload123
Version: 0.1.1
Summary: 
Author: Tzeusy
Author-email: uniquosity@gmail.com
Requires-Python: >=3.8,<4.0
Classifier: Private :: Do Not Upload
Classifier: Programming Language :: Python :: 3
Classifier: Programming Language :: Python :: 3.8
Classifier: Programming Language :: Python :: 3.9
Classifier: Programming Language :: Python :: 3.10
Classifier: Programming Language :: Python :: 3.11
Requires-Dist: devpi-client (==5.2.3)
Requires-Dist: pandas (>=1.5.1,<2.0.0)
